itryid/__init__.py
itryid/client.py
itryid/exceptions.py
itryid/models.py
itryid_sdk-2.0.0.dist-info/METADATA
itryid_sdk-2.0.0.dist-info/WHEEL
itryid_sdk-2.0.0.dist-info/top_level.txt
itryid_sdk-2.0.0.dist-info/RECORD
